<InterfaceSummary>
<RtlPorts>
<name>regs_in_0</name>
<CType>
<TypeName>unsigned int</TypeName>
<TypeWidth>32</TypeWidth>
<PhysicalWidth>32</PhysicalWidth>
</CType>
<CFractionWidth>0</CFractionWidth>
<InvalidType>0</InvalidType>
</RtlPorts>
<RtlPorts>
<name>regs_in_1</name>
<CType>
<TypeName>unsigned int</TypeName>
<TypeWidth>32</TypeWidth>
<PhysicalWidth>32</PhysicalWidth>
</CType>
<CFractionWidth>0</CFractionWidth>
<InvalidType>0</InvalidType>
</RtlPorts>
<RtlPorts>
<name>regs_in_2</name>
<CType>
<TypeName>unsigned int</TypeName>
<TypeWidth>32</TypeWidth>
<PhysicalWidth>32</PhysicalWidth>
</CType>
<CFractionWidth>0</CFractionWidth>
<InvalidType>0</InvalidType>
</RtlPorts>
<RtlPorts>
<name>regs_in_3</name>
<CType>
<TypeName>unsigned int</TypeName>
<TypeWidth>32</TypeWidth>
<PhysicalWidth>32</PhysicalWidth>
</CType>
<CFractionWidth>0</CFractionWidth>
<InvalidType>0</InvalidType>
</RtlPorts>
<RtlPorts>
<name>regs_in_4</name>
<CType>
<TypeName>unsigned int</TypeName>
<TypeWidth>32</TypeWidth>
<PhysicalWidth>32</PhysicalWidth>
</CType>
<CFractionWidth>0</CFractionWidth>
<InvalidType>0</InvalidType>
</RtlPorts>
<RtlPorts>
<name>min_high</name>
<CType>
<TypeName>unsigned int</TypeName>
<TypeWidth>32</TypeWidth>
<PhysicalWidth>32</PhysicalWidth>
</CType>
<CFractionWidth>0</CFractionWidth>
<InvalidType>0</InvalidType>
</RtlPorts>
<RtlPorts>
<name>max_high</name>
<CType>
<TypeName>unsigned int</TypeName>
<TypeWidth>32</TypeWidth>
<PhysicalWidth>32</PhysicalWidth>
</CType>
<CFractionWidth>0</CFractionWidth>
<InvalidType>0</InvalidType>
</RtlPorts>
<RtlPorts>
<name>m_V</name>
<CType>
<TypeName>ap_fixed 16 1 5 3 0</TypeName>
<TypeWidth>16</TypeWidth>
<PhysicalWidth>16</PhysicalWidth>
</CType>
<CFractionWidth>15</CFractionWidth>
<InvalidType>0</InvalidType>
</RtlPorts>
</InterfaceSummary>

