<?xml version="1.0" encoding="utf-8"?>
<Messages>
	<Message prefix="[HLS 200-10]" severity="INFO" keynum="HLS_10_1312" content="Analyzing design file &apos;iiccomm2.cpp&apos; ..." tag=""/>
	<Message prefix="[HLS 200-10]" severity="INFO" keynum="HLS_10_1312" content="Analyzing design file &apos;main.cpp&apos; ..." tag=""/>
	<Message prefix="[HLS 200-10]" severity="INFO" keynum="HLS_10_1465" content="Validating synthesis directives ..." tag=""/>
	<Message prefix="[HLS 200-111]" severity="INFO" keynum="473" content="Finished Checking Pragmas Time (s): cpu = 00:01:21 ; elapsed = 00:00:28 . Memory (MB): peak = 359.941 ; gain = 13.379 ; free physical = 109176 ; free virtual = 500643" tag=""/>
	<Message prefix="[HLS 200-111]" severity="INFO" keynum="473" content="Finished Linking Time (s): cpu = 00:01:23 ; elapsed = 00:00:30 . Memory (MB): peak = 359.941 ; gain = 13.379 ; free physical = 109139 ; free virtual = 500605" tag=""/>
	<Message prefix="[HLS 200-10]" severity="INFO" keynum="HLS_10_1467" content="Starting code transformations ..." tag=""/>
	<Message prefix="[XFORM 203-603]" severity="INFO" keynum="792" content="Inlining function &apos;delay_until_ms&lt;50ull, 50000000ull&gt;&apos; into &apos;iiccomm2&apos; (iiccomm2.cpp:139)." tag=""/>
	<Message prefix="[XFORM 203-603]" severity="INFO" keynum="792" content="Inlining function &apos;delay_until_ms&lt;10ull, 50000000ull&gt;&apos; into &apos;iiccomm2&apos; (iiccomm2.cpp:171)." tag=""/>
	<Message prefix="[XFORM 203-603]" severity="INFO" keynum="792" content="Inlining function &apos;delay_until_ms&lt;10ull, 50000000ull&gt;&apos; into &apos;iiccomm2&apos; (iiccomm2.cpp:157)." tag=""/>
	<Message prefix="[XFORM 203-603]" severity="INFO" keynum="792" content="Inlining function &apos;ap_fixed_base&lt;137, 84, false, (ap_q_mode)5, (ap_o_mode)3, 0&gt;::operator&lt;&lt;&apos; into &apos;generic_cast_IEEE754&lt;unsigned int, (ap_q_mode)6, double&gt;&apos; (/wrk/2017.4/nightly/2017_12_15_2086221/src/products/hls/hls_lib/hlsmath/src/../include/internal/hls_round.h:330)." tag=""/>
	<Message prefix="[XFORM 203-603]" severity="INFO" keynum="792" content="Inlining function &apos;ap_fixed_base&lt;1, 33, false, (ap_q_mode)5, (ap_o_mode)0, 0&gt;::overflow_adjust&apos; into &apos;ap_fixed_base&lt;1, 33, false, (ap_q_mode)5, (ap_o_mode)0, 0&gt;::ap_fixed_base&lt;137, 84, false, (ap_q_mode)5, (ap_o_mode)3, 0&gt;&apos; ()." tag=""/>
	<Message prefix="[HLS 200-111]" severity="INFO" keynum="473" content="Finished Standard Transforms Time (s): cpu = 00:01:25 ; elapsed = 00:00:33 . Memory (MB): peak = 490.984 ; gain = 144.422 ; free physical = 109216 ; free virtual = 500683" tag=""/>
	<Message prefix="[HLS 200-10]" severity="INFO" keynum="HLS_10_1472" content="Checking synthesizability ..." tag=""/>
	<Message prefix="[XFORM 203-602]" severity="INFO" keynum="794" content="Inlining function &apos;fp_struct&lt;double&gt;::mantissa&apos; into &apos;generic_cast_IEEE754&lt;unsigned int, (ap_q_mode)6, double&gt;&apos; (/wrk/2017.4/nightly/2017_12_15_2086221/src/products/hls/hls_lib/hlsmath/src/../include/internal/hls_round.h:327) automatically." tag=""/>
	<Message prefix="[XFORM 203-602]" severity="INFO" keynum="794" content="Inlining function &apos;fp_struct&lt;double&gt;::expv&apos; into &apos;generic_cast_IEEE754&lt;unsigned int, (ap_q_mode)6, double&gt;&apos; (/wrk/2017.4/nightly/2017_12_15_2086221/src/products/hls/hls_lib/hlsmath/src/../include/internal/hls_round.h:330) automatically." tag=""/>
	<Message prefix="[XFORM 203-602]" severity="INFO" keynum="794" content="Inlining function &apos;fp_struct&lt;double&gt;::__signbit&apos; into &apos;generic_cast_IEEE754&lt;unsigned int, (ap_q_mode)6, double&gt;&apos; (/wrk/2017.4/nightly/2017_12_15_2086221/src/products/hls/hls_lib/hlsmath/src/../include/internal/hls_round.h:350) automatically." tag=""/>
	<Message prefix="[XFORM 203-602]" severity="INFO" keynum="794" content="Inlining function &apos;generic_cast_IEEE754&lt;unsigned int, (ap_q_mode)6, double&gt;&apos; into &apos;generic_cast_IEEE754&lt;unsigned int, double&gt;&apos; (/wrk/2017.4/nightly/2017_12_15_2086221/src/products/hls/hls_lib/hlsmath/src/../include/internal/hls_round.h:368) automatically." tag=""/>
	<Message prefix="[XFORM 203-602]" severity="INFO" keynum="794" content="Inlining function &apos;generic_cast_IEEE754&lt;unsigned int, double&gt;&apos; into &apos;__hls_fptoui_double_i32&apos; (/wrk/2017.4/nightly/2017_12_15_2086221/src/products/hls/hls_lib/hlsmath/src/lib_floatconversion.cpp:67) automatically." tag=""/>
	<Message prefix="[XFORM 203-602]" severity="INFO" keynum="794" content="Inlining function &apos;__hls_fptoui_double_i32&apos; into &apos;iiccomm2&apos; (iiccomm2.cpp:227) automatically." tag=""/>
	<Message prefix="[HLS 200-111]" severity="INFO" keynum="473" content="Finished Checking Synthesizability Time (s): cpu = 00:01:27 ; elapsed = 00:00:34 . Memory (MB): peak = 554.184 ; gain = 207.621 ; free physical = 109173 ; free virtual = 500640" tag=""/>
	<Message prefix="[XFORM 203-602]" severity="INFO" keynum="794" content="Inlining function &apos;fp_struct&lt;double&gt;::mantissa&apos; into &apos;generic_cast_IEEE754&lt;unsigned int, (ap_q_mode)6, double&gt;&apos; (/wrk/2017.4/nightly/2017_12_15_2086221/src/products/hls/hls_lib/hlsmath/src/../include/internal/hls_round.h:327) automatically." tag=""/>
	<Message prefix="[XFORM 203-602]" severity="INFO" keynum="794" content="Inlining function &apos;fp_struct&lt;double&gt;::expv&apos; into &apos;generic_cast_IEEE754&lt;unsigned int, (ap_q_mode)6, double&gt;&apos; (/wrk/2017.4/nightly/2017_12_15_2086221/src/products/hls/hls_lib/hlsmath/src/../include/internal/hls_round.h:330) automatically." tag=""/>
	<Message prefix="[XFORM 203-602]" severity="INFO" keynum="794" content="Inlining function &apos;generic_cast_IEEE754&lt;unsigned int, (ap_q_mode)6, double&gt;&apos; into &apos;generic_cast_IEEE754&lt;unsigned int, double&gt;&apos; (/wrk/2017.4/nightly/2017_12_15_2086221/src/products/hls/hls_lib/hlsmath/src/../include/internal/hls_round.h:368) automatically." tag=""/>
	<Message prefix="[XFORM 203-602]" severity="INFO" keynum="794" content="Inlining function &apos;generic_cast_IEEE754&lt;unsigned int, double&gt;&apos; into &apos;__hls_fptoui_double_i32&apos; (/wrk/2017.4/nightly/2017_12_15_2086221/src/products/hls/hls_lib/hlsmath/src/lib_floatconversion.cpp:67) automatically." tag=""/>
	<Message prefix="[XFORM 203-602]" severity="INFO" keynum="794" content="Inlining function &apos;__hls_fptoui_double_i32&apos; into &apos;iiccomm2&apos; (iiccomm2.cpp:227) automatically." tag=""/>
	<Message prefix="[HLS 200-111]" severity="INFO" keynum="473" content="Finished Pre-synthesis Time (s): cpu = 00:01:30 ; elapsed = 00:00:37 . Memory (MB): peak = 554.184 ; gain = 207.621 ; free physical = 109086 ; free virtual = 500553" tag=""/>
	<Message prefix="[HLS 200-111]" severity="INFO" keynum="473" content="Finished Architecture Synthesis Time (s): cpu = 00:01:31 ; elapsed = 00:00:39 . Memory (MB): peak = 554.184 ; gain = 207.621 ; free physical = 108901 ; free virtual = 500368" tag=""/>
	<Message prefix="[HLS 200-10]" severity="INFO" keynum="HLS_10_1317" content="Starting hardware synthesis ..." tag=""/>
	<Message prefix="[HLS 200-10]" severity="INFO" keynum="HLS_10_1385" content="Synthesizing &apos;iiccomm2&apos; ..." tag=""/>
	<Message prefix="[HLS 200-10]" severity="INFO" keynum="HLS_10_1477" content="----------------------------------------------------------------" tag=""/>
	<Message prefix="[HLS 200-42]" severity="INFO" keynum="HLS_42_1438" content="-- Implementing module &apos;iiccomm2&apos;" tag=""/>
	<Message prefix="[HLS 200-10]" severity="INFO" keynum="HLS_10_1478" content="----------------------------------------------------------------" tag=""/>
	<Message prefix="[SCHED 204-11]" severity="INFO" keynum="139" content="Starting scheduling ..." tag=""/>
	<Message prefix="[SCHED 204-21]" severity="WARNING" keynum="86" content="Estimated delay (6.97ns) of &apos;mul&apos; operation (&apos;tmp_48&apos;, iiccomm2.cpp:220) exceeds the target cycle time (target cycle time: 4ns, clock uncertainty: 0.5ns, effective cycle time: 3.5ns)." tag=""/>
	<Message prefix="[SCHED 204-21]" severity="WARNING" keynum="137" content="Estimated clock period (6.973ns) exceeds the target (target clock period: 4ns, clock uncertainty: 0.5ns, effective delay budget: 3.5ns)." tag=""/>
	<Message prefix="[SCHED 204-21]" severity="WARNING" keynum="135" content="The critical path consists of the following:
	&apos;phi&apos; operation (&apos;pressure&apos;) with incoming values : (&apos;pressure&apos;, iiccomm2.cpp:218) (&apos;pressure&apos;, iiccomm2.cpp:214) (0 ns)
	&apos;mul&apos; operation (&apos;tmp_48&apos;, iiccomm2.cpp:220) (6.97 ns)" tag=""/>
	<Message prefix="[SCHED 204-11]" severity="INFO" keynum="138" content="Finished scheduling." tag=""/>
	<Message prefix="[HLS 200-111]" severity="INFO" keynum="474" content=" Elapsed time: 39.5 seconds; current allocated memory: 219.155 MB." tag=""/>
	<Message prefix="[BIND 205-100]" severity="INFO" keynum="439" content="Starting micro-architecture generation ..." tag=""/>
	<Message prefix="[BIND 205-101]" severity="INFO" keynum="211" content="Performing variable lifetime analysis." tag=""/>
	<Message prefix="[BIND 205-101]" severity="INFO" keynum="210" content="Exploring resource sharing." tag=""/>
	<Message prefix="[BIND 205-101]" severity="INFO" keynum="206" content="Binding ..." tag=""/>
	<Message prefix="[BIND 205-100]" severity="INFO" keynum="438" content="Finished micro-architecture generation." tag=""/>
	<Message prefix="[HLS 200-111]" severity="INFO" keynum="474" content=" Elapsed time: 0.6 seconds; current allocated memory: 222.381 MB." tag=""/>
	<Message prefix="[HLS 200-10]" severity="INFO" keynum="HLS_10_1483" content="----------------------------------------------------------------" tag=""/>
	<Message prefix="[HLS 200-10]" severity="INFO" keynum="HLS_10_1484" content="-- Generating RTL for module &apos;iiccomm2&apos;" tag=""/>
	<Message prefix="[HLS 200-10]" severity="INFO" keynum="HLS_10_1485" content="----------------------------------------------------------------" tag=""/>
	<Message prefix="[RTGEN 206-500]" severity="INFO" keynum="73" content="Setting interface mode on port &apos;iiccomm2/iic&apos; to &apos;m_axi&apos;." tag=""/>
	<Message prefix="[RTGEN 206-500]" severity="INFO" keynum="73" content="Setting interface mode on port &apos;iiccomm2/empty_pirq_outValue&apos; to &apos;s_axilite &amp; ap_vld&apos;." tag=""/>
	<Message prefix="[RTGEN 206-500]" severity="INFO" keynum="73" content="Setting interface mode on port &apos;iiccomm2/full_pirq_outValue&apos; to &apos;s_axilite &amp; ap_vld&apos;." tag=""/>
	<Message prefix="[RTGEN 206-500]" severity="INFO" keynum="73" content="Setting interface mode on port &apos;iiccomm2/ctrl_reg_outValue&apos; to &apos;s_axilite &amp; ap_vld&apos;." tag=""/>
	<Message prefix="[RTGEN 206-500]" severity="INFO" keynum="73" content="Setting interface mode on port &apos;iiccomm2/stat_reg_outValue1&apos; to &apos;s_axilite &amp; ap_vld&apos;." tag=""/>
	<Message prefix="[RTGEN 206-500]" severity="INFO" keynum="73" content="Setting interface mode on port &apos;iiccomm2/stat_reg_val2&apos; to &apos;s_axilite &amp; ap_vld&apos;." tag=""/>
	<Message prefix="[RTGEN 206-500]" severity="INFO" keynum="73" content="Setting interface mode on port &apos;iiccomm2/pressure_msb&apos; to &apos;s_axilite &amp; ap_vld&apos;." tag=""/>
	<Message prefix="[RTGEN 206-500]" severity="INFO" keynum="73" content="Setting interface mode on port &apos;iiccomm2/pressure_lsb&apos; to &apos;s_axilite &amp; ap_vld&apos;." tag=""/>
	<Message prefix="[RTGEN 206-500]" severity="INFO" keynum="73" content="Setting interface mode on port &apos;iiccomm2/pressure_xlsb&apos; to &apos;s_axilite &amp; ap_vld&apos;." tag=""/>
	<Message prefix="[RTGEN 206-500]" severity="INFO" keynum="73" content="Setting interface mode on port &apos;iiccomm2/temp_msb&apos; to &apos;s_axilite &amp; ap_vld&apos;." tag=""/>
	<Message prefix="[RTGEN 206-500]" severity="INFO" keynum="73" content="Setting interface mode on port &apos;iiccomm2/temp_lsb&apos; to &apos;s_axilite &amp; ap_vld&apos;." tag=""/>
	<Message prefix="[RTGEN 206-500]" severity="INFO" keynum="73" content="Setting interface mode on port &apos;iiccomm2/temp_xlsb&apos; to &apos;s_axilite &amp; ap_vld&apos;." tag=""/>
	<Message prefix="[RTGEN 206-500]" severity="INFO" keynum="73" content="Setting interface mode on port &apos;iiccomm2/press_raw&apos; to &apos;s_axilite &amp; ap_vld&apos;." tag=""/>
	<Message prefix="[RTGEN 206-500]" severity="INFO" keynum="73" content="Setting interface mode on port &apos;iiccomm2/temp_raw&apos; to &apos;s_axilite &amp; ap_vld&apos;." tag=""/>
	<Message prefix="[RTGEN 206-500]" severity="INFO" keynum="73" content="Setting interface mode on port &apos;iiccomm2/operation&apos; to &apos;s_axilite &amp; ap_vld&apos;." tag=""/>
	<Message prefix="[RTGEN 206-500]" severity="INFO" keynum="73" content="Setting interface mode on port &apos;iiccomm2/press_cal&apos; to &apos;s_axilite &amp; ap_vld&apos;." tag=""/>
	<Message prefix="[RTGEN 206-500]" severity="INFO" keynum="73" content="Setting interface mode on port &apos;iiccomm2/press_act&apos; to &apos;s_axilite &amp; ap_vld&apos;." tag=""/>
	<Message prefix="[RTGEN 206-500]" severity="INFO" keynum="73" content="Setting interface mode on function &apos;iiccomm2&apos; to &apos;s_axilite &amp; ap_ctrl_hs&apos;." tag=""/>
	<Message prefix="[RTGEN 206-100]" severity="INFO" keynum="364" content="Bundling port &apos;return&apos;, &apos;full_pirq_outValue&apos;, &apos;ctrl_reg_outValue&apos;, &apos;stat_reg_outValue1&apos;, &apos;stat_reg_val2&apos;, &apos;pressure_msb&apos;, &apos;pressure_lsb&apos;, &apos;pressure_xlsb&apos;, &apos;temp_msb&apos;, &apos;temp_lsb&apos;, &apos;temp_xlsb&apos;, &apos;press_raw&apos;, &apos;temp_raw&apos;, &apos;operation&apos;, &apos;press_cal&apos; and &apos;press_act&apos; to AXI-Lite port AXILiteS." tag=""/>
	<Message prefix="[SYN 201-210]" severity="INFO" keynum="402" content="Renamed object name &apos;iiccomm2_ddiv_64ns_64ns_64_59_1&apos; to &apos;iiccomm2_ddiv_64nbkb&apos; due to the length limit 20" tag=""/>
	<Message prefix="[SYN 201-210]" severity="INFO" keynum="402" content="Renamed object name &apos;iiccomm2_uitodp_32ns_64_8_1&apos; to &apos;iiccomm2_uitodp_3cud&apos; due to the length limit 20" tag=""/>
	<Message prefix="[SYN 201-210]" severity="INFO" keynum="402" content="Renamed object name &apos;iiccomm2_mul_29s_29s_57_7_1&apos; to &apos;iiccomm2_mul_29s_dEe&apos; due to the length limit 20" tag=""/>
	<Message prefix="[SYN 201-210]" severity="INFO" keynum="402" content="Renamed object name &apos;iiccomm2_mul_7ns_45s_51_12_1&apos; to &apos;iiccomm2_mul_7ns_eOg&apos; due to the length limit 20" tag=""/>
	<Message prefix="[SYN 201-210]" severity="INFO" keynum="402" content="Renamed object name &apos;iiccomm2_mul_16ns_29ns_44_7_1&apos; to &apos;iiccomm2_mul_16nsfYi&apos; due to the length limit 20" tag=""/>
	<Message prefix="[SYN 201-210]" severity="INFO" keynum="402" content="Renamed object name &apos;iiccomm2_mul_52s_52s_64_6_1&apos; to &apos;iiccomm2_mul_52s_g8j&apos; due to the length limit 20" tag=""/>
	<Message prefix="[SYN 201-210]" severity="INFO" keynum="402" content="Renamed object name &apos;iiccomm2_mul_18ns_45s_64_12_1&apos; to &apos;iiccomm2_mul_18nshbi&apos; due to the length limit 20" tag=""/>
	<Message prefix="[SYN 201-210]" severity="INFO" keynum="402" content="Renamed object name &apos;iiccomm2_mul_17ns_45s_64_12_1&apos; to &apos;iiccomm2_mul_17nsibs&apos; due to the length limit 20" tag=""/>
	<Message prefix="[SYN 201-210]" severity="INFO" keynum="402" content="Renamed object name &apos;iiccomm2_mul_17ns_53s_64_6_1&apos; to &apos;iiccomm2_mul_17nsjbC&apos; due to the length limit 20" tag=""/>
	<Message prefix="[SYN 201-210]" severity="INFO" keynum="402" content="Renamed object name &apos;iiccomm2_mul_13ns_51s_63_6_1&apos; to &apos;iiccomm2_mul_13nskbM&apos; due to the length limit 20" tag=""/>
	<Message prefix="[SYN 201-210]" severity="INFO" keynum="402" content="Renamed object name &apos;iiccomm2_add_64ns_64ns_64_2_1&apos; to &apos;iiccomm2_add_64nslbW&apos; due to the length limit 20" tag=""/>
	<Message prefix="[SYN 201-210]" severity="INFO" keynum="402" content="Renamed object name &apos;iiccomm2_mul_17ns_46s_62_12_1&apos; to &apos;iiccomm2_mul_17nsmb6&apos; due to the length limit 20" tag=""/>
	<Message prefix="[SYN 201-210]" severity="INFO" keynum="402" content="Renamed object name &apos;iiccomm2_mul_13ns_52s_63_6_1&apos; to &apos;iiccomm2_mul_13nsncg&apos; due to the length limit 20" tag=""/>
	<Message prefix="[SYN 201-210]" severity="INFO" keynum="402" content="Renamed object name &apos;iiccomm2_mul_52s_14ns_64_6_1&apos; to &apos;iiccomm2_mul_52s_ocq&apos; due to the length limit 20" tag=""/>
	<Message prefix="[SYN 201-210]" severity="INFO" keynum="402" content="Renamed object name &apos;iiccomm2_udiv_63ns_47s_63_67_1&apos; to &apos;iiccomm2_udiv_63npcA&apos; due to the length limit 20" tag=""/>
	<Message prefix="[SYN 201-210]" severity="INFO" keynum="402" content="Renamed object name &apos;iiccomm2_udiv_64ns_47s_64_68_1&apos; to &apos;iiccomm2_udiv_64nqcK&apos; due to the length limit 20" tag=""/>
	<Message prefix="[SYN 201-210]" severity="INFO" keynum="402" content="Renamed object name &apos;iiccomm2_mul_61s_61s_61_7_1&apos; to &apos;iiccomm2_mul_61s_rcU&apos; due to the length limit 20" tag=""/>
	<Message prefix="[SYN 201-210]" severity="INFO" keynum="402" content="Renamed object name &apos;iiccomm2_mul_17ns_49s_49_12_1&apos; to &apos;iiccomm2_mul_17nssc4&apos; due to the length limit 20" tag=""/>
	<Message prefix="[SYN 201-210]" severity="INFO" keynum="402" content="Renamed object name &apos;iiccomm2_mul_14ns_48s_48_12_1&apos; to &apos;iiccomm2_mul_14nstde&apos; due to the length limit 20" tag=""/>
	<Message prefix="[SYN 201-210]" severity="INFO" keynum="402" content="Renamed object name &apos;iiccomm2_lshr_54ns_32ns_54_7_1&apos; to &apos;iiccomm2_lshr_54nudo&apos; due to the length limit 20" tag=""/>
	<Message prefix="[SYN 201-210]" severity="INFO" keynum="402" content="Renamed object name &apos;iiccomm2_shl_137ns_32ns_137_7_1&apos; to &apos;iiccomm2_shl_137nvdy&apos; due to the length limit 20" tag=""/>
	<Message prefix="[RTGEN 206-100]" severity="INFO" keynum="368" content="Generating core module &apos;iiccomm2_add_64nslbW&apos;: 1 instance(s)." tag=""/>
	<Message prefix="[RTGEN 206-100]" severity="INFO" keynum="368" content="Generating core module &apos;iiccomm2_ddiv_64nbkb&apos;: 1 instance(s)." tag=""/>
	<Message prefix="[RTGEN 206-100]" severity="INFO" keynum="368" content="Generating core module &apos;iiccomm2_lshr_54nudo&apos;: 1 instance(s)." tag=""/>
	<Message prefix="[RTGEN 206-100]" severity="INFO" keynum="368" content="Generating core module &apos;iiccomm2_mul_13nskbM&apos;: 1 instance(s)." tag=""/>
	<Message prefix="[RTGEN 206-100]" severity="INFO" keynum="368" content="Generating core module &apos;iiccomm2_mul_13nsncg&apos;: 1 instance(s)." tag=""/>
	<Message prefix="[RTGEN 206-100]" severity="INFO" keynum="368" content="Generating core module &apos;iiccomm2_mul_14nstde&apos;: 1 instance(s)." tag=""/>
	<Message prefix="[RTGEN 206-100]" severity="INFO" keynum="368" content="Generating core module &apos;iiccomm2_mul_16nsfYi&apos;: 1 instance(s)." tag=""/>
	<Message prefix="[RTGEN 206-100]" severity="INFO" keynum="368" content="Generating core module &apos;iiccomm2_mul_17nsibs&apos;: 1 instance(s)." tag=""/>
	<Message prefix="[RTGEN 206-100]" severity="INFO" keynum="368" content="Generating core module &apos;iiccomm2_mul_17nsjbC&apos;: 1 instance(s)." tag=""/>
	<Message prefix="[RTGEN 206-100]" severity="INFO" keynum="368" content="Generating core module &apos;iiccomm2_mul_17nsmb6&apos;: 1 instance(s)." tag=""/>
	<Message prefix="[RTGEN 206-100]" severity="INFO" keynum="368" content="Generating core module &apos;iiccomm2_mul_17nssc4&apos;: 1 instance(s)." tag=""/>
	<Message prefix="[RTGEN 206-100]" severity="INFO" keynum="368" content="Generating core module &apos;iiccomm2_mul_18nshbi&apos;: 1 instance(s)." tag=""/>
	<Message prefix="[RTGEN 206-100]" severity="INFO" keynum="368" content="Generating core module &apos;iiccomm2_mul_29s_dEe&apos;: 1 instance(s)." tag=""/>
	<Message prefix="[RTGEN 206-100]" severity="INFO" keynum="368" content="Generating core module &apos;iiccomm2_mul_52s_g8j&apos;: 1 instance(s)." tag=""/>
	<Message prefix="[RTGEN 206-100]" severity="INFO" keynum="368" content="Generating core module &apos;iiccomm2_mul_52s_ocq&apos;: 1 instance(s)." tag=""/>
	<Message prefix="[RTGEN 206-100]" severity="INFO" keynum="368" content="Generating core module &apos;iiccomm2_mul_61s_rcU&apos;: 1 instance(s)." tag=""/>
	<Message prefix="[RTGEN 206-100]" severity="INFO" keynum="368" content="Generating core module &apos;iiccomm2_mul_7ns_eOg&apos;: 1 instance(s)." tag=""/>
	<Message prefix="[RTGEN 206-100]" severity="INFO" keynum="368" content="Generating core module &apos;iiccomm2_shl_137nvdy&apos;: 1 instance(s)." tag=""/>
	<Message prefix="[RTGEN 206-100]" severity="INFO" keynum="368" content="Generating core module &apos;iiccomm2_udiv_63npcA&apos;: 1 instance(s)." tag=""/>
	<Message prefix="[RTGEN 206-100]" severity="INFO" keynum="368" content="Generating core module &apos;iiccomm2_udiv_64nqcK&apos;: 1 instance(s)." tag=""/>
	<Message prefix="[RTGEN 206-100]" severity="INFO" keynum="368" content="Generating core module &apos;iiccomm2_uitodp_3cud&apos;: 1 instance(s)." tag=""/>
	<Message prefix="[RTGEN 206-100]" severity="INFO" keynum="369" content="Finished creating RTL model for &apos;iiccomm2&apos;." tag=""/>
	<Message prefix="[HLS 200-111]" severity="INFO" keynum="474" content=" Elapsed time: 0.85 seconds; current allocated memory: 228.243 MB." tag=""/>
	<Message prefix="[RTMG 210-282]" severity="INFO" keynum="RTMG_282_1796" content="Generating pipelined core: &apos;iiccomm2_mul_29s_dEe_MulnS_0&apos;" tag=""/>
	<Message prefix="[RTMG 210-282]" severity="INFO" keynum="RTMG_282_1796" content="Generating pipelined core: &apos;iiccomm2_mul_7ns_eOg_MulnS_1&apos;" tag=""/>
	<Message prefix="[RTMG 210-282]" severity="INFO" keynum="RTMG_282_1796" content="Generating pipelined core: &apos;iiccomm2_mul_16nsfYi_MulnS_2&apos;" tag=""/>
	<Message prefix="[RTMG 210-282]" severity="INFO" keynum="RTMG_282_1796" content="Generating pipelined core: &apos;iiccomm2_mul_52s_g8j_Mul6S_0&apos;" tag=""/>
	<Message prefix="[RTMG 210-282]" severity="INFO" keynum="RTMG_282_1796" content="Generating pipelined core: &apos;iiccomm2_mul_18nshbi_MulnS_3&apos;" tag=""/>
	<Message prefix="[RTMG 210-282]" severity="INFO" keynum="RTMG_282_1796" content="Generating pipelined core: &apos;iiccomm2_mul_17nsibs_MulnS_4&apos;" tag=""/>
	<Message prefix="[RTMG 210-282]" severity="INFO" keynum="RTMG_282_1796" content="Generating pipelined core: &apos;iiccomm2_mul_17nsjbC_Mul6S_1&apos;" tag=""/>
	<Message prefix="[RTMG 210-282]" severity="INFO" keynum="RTMG_282_1796" content="Generating pipelined core: &apos;iiccomm2_mul_13nskbM_Mul6S_2&apos;" tag=""/>
	<Message prefix="[RTMG 210-283]" severity="INFO" keynum="RTMG_283_1797" content="Generating pipelined adder/subtractor : &apos;iiccomm2_add_64nslbW_AddSubnS_0&apos;" tag=""/>
	<Message prefix="[RTMG 210-282]" severity="INFO" keynum="RTMG_282_1796" content="Generating pipelined core: &apos;iiccomm2_mul_17nsmb6_MulnS_5&apos;" tag=""/>
	<Message prefix="[RTMG 210-282]" severity="INFO" keynum="RTMG_282_1796" content="Generating pipelined core: &apos;iiccomm2_mul_13nsncg_Mul6S_3&apos;" tag=""/>
	<Message prefix="[RTMG 210-282]" severity="INFO" keynum="RTMG_282_1796" content="Generating pipelined core: &apos;iiccomm2_mul_52s_ocq_Mul6S_4&apos;" tag=""/>
	<Message prefix="[RTMG 210-282]" severity="INFO" keynum="RTMG_282_1796" content="Generating pipelined core: &apos;iiccomm2_udiv_63npcA_div&apos;" tag=""/>
	<Message prefix="[RTMG 210-282]" severity="INFO" keynum="RTMG_282_1796" content="Generating pipelined core: &apos;iiccomm2_udiv_64nqcK_div&apos;" tag=""/>
	<Message prefix="[RTMG 210-282]" severity="INFO" keynum="RTMG_282_1796" content="Generating pipelined core: &apos;iiccomm2_mul_61s_rcU_MulnS_6&apos;" tag=""/>
	<Message prefix="[RTMG 210-282]" severity="INFO" keynum="RTMG_282_1796" content="Generating pipelined core: &apos;iiccomm2_mul_17nssc4_MulnS_7&apos;" tag=""/>
	<Message prefix="[RTMG 210-282]" severity="INFO" keynum="RTMG_282_1796" content="Generating pipelined core: &apos;iiccomm2_mul_14nstde_MulnS_8&apos;" tag=""/>
	<Message prefix="[RTMG 210-286]" severity="INFO" keynum="RTMG_286_1800" content="Generating pipelined shifter : &apos;iiccomm2_lshr_54nudo&apos;" tag=""/>
	<Message prefix="[RTMG 210-286]" severity="INFO" keynum="RTMG_286_1800" content="Generating pipelined shifter : &apos;iiccomm2_shl_137nvdy&apos;" tag=""/>
	<Message prefix="[RTMG 210-278]" severity="INFO" keynum="RTMG_278_1790" content="Implementing memory &apos;iiccomm2_sensorData_ram (RAM)&apos; using block RAMs." tag=""/>
	<Message prefix="[HLS 200-111]" severity="INFO" keynum="473" content="Finished generating all RTL models Time (s): cpu = 00:01:35 ; elapsed = 00:00:43 . Memory (MB): peak = 554.184 ; gain = 207.621 ; free physical = 109113 ; free virtual = 500534" tag=""/>
	<Message prefix="[SYSC 207-301]" severity="INFO" keynum="SYSC_301_1065" content="Generating SystemC RTL for iiccomm2." tag=""/>
	<Message prefix="[VHDL 208-304]" severity="INFO" keynum="VHDL_304_1066" content="Generating VHDL RTL for iiccomm2." tag=""/>
	<Message prefix="[VLOG 209-307]" severity="INFO" keynum="VLOG_307_1067" content="Generating Verilog RTL for iiccomm2." tag=""/>
</Messages>
